{
  "version": "2.0",
  "routeKey": "GET /posts",
  "rawPath": "/dev/posts",
  "rawQueryString": "",
  "headers": {
    "accept": "*/*",
    "accept-encoding": "gzip, deflate, br",
    "content-length": "0",
    "host": "7lra7r1o0i.execute-api.eu-west-1.amazonaws.com",
    "postman-token": "afcb61a4-9583-4a3c-9201-36e1ada3832a",
    "user-agent": "PostmanRuntime/7.26.3",
    "x-amzn-trace-id": "Root=1-5f47c007-7b920e7e60bd9b64661743f7",
    "x-forwarded-for": "37.57.69.132",
    "x-forwarded-port": "443",
    "x-forwarded-proto": "https"
  },
  "requestContext": {
    "accountId": "813315352955",
    "apiId": "7lra7r1o0i",
    "domainName": "7lra7r1o0i.execute-api.eu-west-1.amazonaws.com",
    "domainPrefix": "7lra7r1o0i",
    "http": {
      "method": "GET",
      "path": "/dev/posts",
      "protocol": "HTTP/1.1",
      "sourceIp": "37.57.69.132",
      "userAgent": "PostmanRuntime/7.26.3"
    },
    "requestId": "R7rxJiubjoEEP9Q=",
    "routeKey": "GET /posts",
    "stage": "dev",
    "time": "27/Aug/2020:14:15:35 +0000",
    "timeEpoch": 1598537735262
  },
  "isBase64Encoded": false
}